LICENSE
MANIFEST.in
README.md
husl.py
setup.py
husl.egg-info/PKG-INFO
husl.egg-info/SOURCES.txt
husl.egg-info/dependency_links.txt
husl.egg-info/top_level.txt