Metadata-Version: 1.1
Name: husl
Version: 4.0.2
Summary: Human-friendly HSL
Home-page: http://www.husl-colors.org
Author: UNKNOWN
Author-email: alexei@boronine.com
License: MIT
Keywords: color hsl cie cieluv colorwheel
Platform: UNKNOWN
Classifier: Development Status :: 4 - Beta
Classifier: Intended Audience :: Developers
Classifier: License :: OSI Approved :: MIT License
Classifier: Operating System :: OS Independent
Classifier: Topic :: Software Development
